{
	"configurations" : 
	[
		{
			"directories" : 
			[
				{
					"build" : ".",
					"jsonFile" : "directory-.-Debug-d0094a50bb2071803777.json",
					"minimumCMakeVersion" : 
					{
						"string" : "3.23"
					},
					"projectIndex" : 0,
					"source" : ".",
					"targetIndexes" : 
					[
						0
					]
				}
			],
			"name" : "Debug",
			"projects" : 
			[
				{
					"directoryIndexes" : 
					[
						0
					],
					"name" : "AerspGithub",
					"targetIndexes" : 
					[
						0
					]
				}
			],
			"targets" : 
			[
				{
					"directoryIndex" : 0,
					"id" : "executablefile::@6890427a1f51a3e7e1df",
					"jsonFile" : "target-executablefile-Debug-2d035564e4c115715e01.json",
					"name" : "executablefile",
					"projectIndex" : 0
				}
			]
		}
	],
	"kind" : "codemodel",
	"paths" : 
	{
		"build" : "C:/Users/andre/OneDrive/Documents/Penn State/AERSP 424/CodingHW1/out/build/x64-Debug",
		"source" : "C:/Users/andre/OneDrive/Documents/Penn State/AERSP 424/CodingHW1"
	},
	"version" : 
	{
		"major" : 2,
		"minor" : 4
	}
}
